.coveragerc
.gitignore
.gitlab-ci.yml
LICENSE
MAINTAINERS
MANIFEST.in
NEWS
README.rst
conftest.py
setup.cfg
setup.py
BuildStream_external.egg-info/PKG-INFO
BuildStream_external.egg-info/SOURCES.txt
BuildStream_external.egg-info/dependency_links.txt
BuildStream_external.egg-info/entry_points.txt
BuildStream_external.egg-info/not-zip-safe
BuildStream_external.egg-info/requires.txt
BuildStream_external.egg-info/top_level.txt
bst_external/__init__.py
bst_external/elements/__init__.py
bst_external/elements/check_forbidden.py
bst_external/elements/collect_integration.py
bst_external/elements/collect_manifest.py
bst_external/elements/dpkg_build.py
bst_external/elements/dpkg_build.yaml
bst_external/elements/dpkg_deploy.py
bst_external/elements/dpkg_deploy.yaml
bst_external/elements/fastboot_bootimg.py
bst_external/elements/fastboot_bootimg.yaml
bst_external/elements/fastboot_ext4.py
bst_external/elements/fastboot_ext4.yaml
bst_external/elements/flatpak_image.py
bst_external/elements/flatpak_image.yaml
bst_external/elements/flatpak_repo.py
bst_external/elements/flatpak_repo.yaml
bst_external/elements/oci.py
bst_external/elements/snap_image.py
bst_external/elements/snap_image.yaml
bst_external/elements/tar_element.py
bst_external/elements/tar_element.yaml
bst_external/elements/x86image.py
bst_external/elements/x86image.yaml
bst_external/sources/__init__.py
bst_external/sources/cargo.py
bst_external/sources/cpan.py
bst_external/sources/docker.py
bst_external/sources/git_module.py
bst_external/sources/git_tag.py
bst_external/sources/patch_queue.py
bst_external/sources/pypi.py
bst_external/sources/quilt.py
doc/Makefile
doc/sphinx-build3
doc/source/conf.py
doc/source/index.rst
doc/source/plugin.rsttemplate
tests/__init__.py
tests/docker-source.py
tests/dpkg.py
tests/git_tag.py
tests/quilt.py
tests/tar_element.py
tests/git_tag/lfs/project.conf
tests/git_tag/project-override/project.conf
tests/git_tag/project-override/repofiles/file.txt
tests/git_tag/project-override/subrepofiles/ponyfile.txt
tests/git_tag/template/project.conf
tests/git_tag/template/inconsistent-submodule/.gitmodules
tests/git_tag/template/othersubrepofiles/unicornfile.txt
tests/git_tag/template/repofiles/file.txt
tests/git_tag/template/subrepofiles/ponyfile.txt
tests/project/project.conf
