Metadata-Version: 2.1
Name: BuildStream-external
Version: 0.28.1
Summary: A collection of BuildStream plugins that don't fit in with the core plugins for whatever reason.
License: LGPL
License-File: LICENSE
